pidentity/__init__.py
pidentity/conditions.py
pidentity/constants.py
pidentity/contract.py
pidentity/control.py
pidentity/controller.py
pidentity/database.py
pidentity/lookup.py
pidentity/macros.py
pidentity/operators.py
pidentity/rules.py
pidentity-0.1.3.dist-info/METADATA
pidentity-0.1.3.dist-info/WHEEL
pidentity-0.1.3.dist-info/RECORD
