Metadata-Version: 2.1
Name: pidentity
Version: 0.1.3
Summary: The Simplest Attribute Based Access Control Python Library
Author: Raymond
Author-email: ortserga@gmail.com
Requires-Python: >=3.7,<4.0
Classifier: Programming Language :: Python :: 3
Classifier: Programming Language :: Python :: 3.7
Classifier: Programming Language :: Python :: 3.8
Classifier: Programming Language :: Python :: 3.9
Classifier: Programming Language :: Python :: 3.10
Classifier: Programming Language :: Python :: 3.11
